ALU\SignExtender/SignExtender.v
module SignExtender(BusImm, Imm26, Ctrl); 
    output reg [63:0] BusImm; 
    input [25:0] Imm26; 
    input [1:0] Ctrl; 

    // I-type extends immediate
    // D-type extends address  

    reg extBit; 

    // if statement to grab correct bits to extend
    always @(*) begin
        if (Ctrl == 2'b00) begin // I-type
            extBit = 0; // Most significant bit
            BusImm = {{52{extBit}}, Imm26[21:10]}; // Extend only immediate part to 64, add whole immediate
        end

        else if (Ctrl == 2'b01) begin // D-type
            extBit = Imm26[20]; 
            BusImm = {{55{extBit}}, Imm26[20:12]}; 
        end

        else if (Ctrl == 2'b10) begin // B-type
            extBit = Imm26[25]; 
            BusImm = {{38{extBit}}, Imm26[25:0]}; 
        end

        else begin // CB-type
            extBit = Imm26[23];
            BusImm = {{45{extBit}}, Imm26[23:5]};
        end
    end

    // assign extBit = (Ctrl ? 1'b0 : Imm16[15]); can't do this, need if statement for each type
    // assign BusImm = {{16{extBit}}, Imm16}; Actual extension of bit, specific to type

endmodule

Lab07/SignExtenderTest.v
`timescale 1ns / 1ps

////////////////////////////////////////////////////////////////////////////////
// Company: 
// Engineer:
//
// Create Date:   15:06:33 03/02/2009
// Design Name:   SignExtender
// Module Name:   E:/350/Lab7/SignExtenderTest.v
// Project Name:  SignExtender
// Target Device:  
// Tool versions:  
// Description: 
//
// Verilog Test Fixture created by ISE for module: SignExtender
//
// Dependencies:
// 
// Revision:
// Revision 0.01 - File Created
// Additional Comments:
// 
////////////////////////////////////////////////////////////////////////////////

`define STRLEN 15
module SignExtenderTest_v;
initial //This initial block used to dump all wire/reg values to dump file
    begin
     $dumpfile("SignExtender.vcd"); // Fixed dump
     $dumpvars(0,SignExtenderTest_v);
    end
	task passTest;
		input [63:0] actualOut, expectedOut; // Output correct size, everything else copied
		input [`STRLEN*8:0] testType;
		inout [7:0] passed;
        // Checking if correct
		if(actualOut == expectedOut) begin $display ("%s passed", testType); passed = passed + 1; end
		else $display ("%s failed: %d should be %d", testType, actualOut, expectedOut);
	endtask
	
	task allPassed; // Checking if all passed
		input [7:0] passed;
		input [7:0] numTests;
		
		if(passed == numTests) $display ("All tests passed");
		else $display("Some tests failed");
	endtask
	
	task stim;
		input [25:0] newImm26; // Create new and set for inputs
		input [1:0] newCtrl;
		output [25:0] setImm26;
        output [1:0] setCtrl;
		
		begin
			#90;
			setImm26 = newImm26; // Change old to new
			setCtrl = newCtrl;
		end
	endtask
	
	// Inputs
	reg [25:0] Imm26;
	reg [1:0] Ctrl;
	reg [7:0] passed;

	// Outputs
	wire [63:0] BusImm;

	// Instantiate the Unit Under Test (UUT)
	SignExtender uut (
		.BusImm(BusImm), 
		.Imm26(Imm26), 
		.Ctrl(Ctrl)
	);

	initial begin
		// Initialize Inputs
		Imm26 = 26'b00000000000000000000000000;
		Ctrl = 2'b00;
		passed = 0;

		/* Create test cases
        stim(Imm26 input, ctrl input, input1, input2); wait a little passTest(output1, expected value, tested type, call passed)
        */

		stim(26'b10100101011010110100011010, 2'b00, Imm26, Ctrl); #10; passTest(BusImm, 64'b010101101011, "I-type pos", passed);
		stim(26'b10101101010010110101111000, 2'b00, Imm26, Ctrl); #10; passTest(BusImm, 64'b110101001011, "I-type neg", passed);
		stim(26'b01011010110101111010100101, 2'b01, Imm26, Ctrl); #10; passTest(BusImm, 64'b010110101, "D-type pos", passed);
		stim(26'b01110100110101010101010111, 2'b01, Imm26, Ctrl); #10; passTest(BusImm, 64'b1111111111111111111111111111111111111111111111111111111100110101, "D-type neg", passed);
		stim(26'b00110101011111101011010100, 2'b10, Imm26, Ctrl); #10; passTest(BusImm, 64'b00110101011111101011010100, "B-type pos", passed);
		stim(26'b10110100101000101110101001, 2'b10, Imm26, Ctrl); #10; passTest(BusImm, 64'b1111111111111111111111111111111111111110110100101000101110101001, "B-type neg", passed);
		stim(26'b11000101101011001010100011, 2'b11, Imm26, Ctrl); #10; passTest(BusImm, 64'b0001011010110010101, "CB-type pos", passed);
		stim(26'b11110100110100101001011011, 2'b11, Imm26, Ctrl); #10; passTest(BusImm, 64'b1111111111111111111111111111111111111111111111101001101001010010, "CB-type neg", passed);
		#10;
		
		allPassed(passed, 8); // Checking if everything worked
	end
      
endmodule

Lab07/SignExtender.vcd
$date
	Thu Jun  5 14:10:17 2025
$end
$version
	Icarus Verilog
$end
$timescale
	1ps
$end
$scope module SignExtenderTest_v $end
$var wire 64 ! BusImm [63:0] $end
$var reg 2 " Ctrl [1:0] $end
$var reg 26 # Imm26 [25:0] $end
$var reg 8 $ passed [7:0] $end
$scope module uut $end
$var wire 2 % Ctrl [1:0] $end
$var wire 26 & Imm26 [25:0] $end
$var reg 64 ' BusImm [63:0] $end
$var reg 1 ( extBit $end
$upscope $end
$scope task allPassed $end
$var reg 8 ) numTests [7:0] $end
$var reg 8 * passed [7:0] $end
$upscope $end
$scope task passTest $end
$var reg 64 + actualOut [63:0] $end
$var reg 64 , expectedOut [63:0] $end
$var reg 8 - passed [7:0] $end
$var reg 121 . testType [120:0] $end
$upscope $end
$scope task stim $end
$var reg 2 / newCtrl [1:0] $end
$var reg 26 0 newImm26 [25:0] $end
$var reg 2 1 setCtrl [1:0] $end
$var reg 26 2 setImm26 [25:0] $end
$upscope $end
$upscope $end
$enddefinitions $end
#0
$dumpvars
bx 2
bx 1
b10100101011010110100011010 0
b0 /
bx .
bx -
bx ,
bx +
bx *
bx )
0(
b0 '
b0 &
b0 %
b0 $
b0 #
b0 "
b0 !
$end
#90000
b10101101011 !
b10101101011 '
b10100101011010110100011010 #
b10100101011010110100011010 &
b0 1
b10100101011010110100011010 2
#100000
b10101101010010110101111000 0
b1 $
b1 -
b1001001001011010111010001111001011100000110010100100000011100000110111101110011 .
b10101101011 ,
b10101101011 +
#190000
b110101001011 !
b110101001011 '
b10101101010010110101111000 #
b10101101010010110101111000 &
b10101101010010110101111000 2
#200000
b1 /
b1011010110101111010100101 0
b10 $
b10 -
b1001001001011010111010001111001011100000110010100100000011011100110010101100111 .
b110101001011 ,
b110101001011 +
#290000
b10110101 !
b10110101 '
b1 "
b1 %
b1011010110101111010100101 #
b1011010110101111010100101 &
b1 1
b1011010110101111010100101 2
#300000
b1110100110101010101010111 0
b11 $
b11 -
b1000100001011010111010001111001011100000110010100100000011100000110111101110011 .
b10110101 ,
b10110101 +
#390000
b1111111111111111111111111111111111111111111111111111111100110101 !
b1111111111111111111111111111111111111111111111111111111100110101 '
1(
b1110100110101010101010111 #
b1110100110101010101010111 &
b1110100110101010101010111 2
#400000
b10 /
b110101011111101011010100 0
b100 $
b100 -
b1000100001011010111010001111001011100000110010100100000011011100110010101100111 .
b1111111111111111111111111111111111111111111111111111111100110101 ,
b1111111111111111111111111111111111111111111111111111111100110101 +
#490000
b110101011111101011010100 !
b110101011111101011010100 '
0(
b10 "
b10 %
b110101011111101011010100 #
b110101011111101011010100 &
b10 1
b110101011111101011010100 2
#500000
b10110100101000101110101001 0
b101 $
b101 -
b1000010001011010111010001111001011100000110010100100000011100000110111101110011 .
b110101011111101011010100 ,
b110101011111101011010100 +
#590000
b1111111111111111111111111111111111111110110100101000101110101001 !
b1111111111111111111111111111111111111110110100101000101110101001 '
1(
b10110100101000101110101001 #
b10110100101000101110101001 &
b10110100101000101110101001 2
#600000
b11 /
b11000101101011001010100011 0
b110 $
b110 -
b1000010001011010111010001111001011100000110010100100000011011100110010101100111 .
b1111111111111111111111111111111111111110110100101000101110101001 ,
b1111111111111111111111111111111111111110110100101000101110101001 +
#690000
b1011010110010101 !
b1011010110010101 '
0(
b11 "
b11 %
b11000101101011001010100011 #
b11000101101011001010100011 &
b11 1
b11000101101011001010100011 2
#700000
b11110100110100101001011011 0
b111 $
b111 -
b100001101000010001011010111010001111001011100000110010100100000011100000110111101110011 .
b1011010110010101 ,
b1011010110010101 +
#790000
b1111111111111111111111111111111111111111111111101001101001010010 !
b1111111111111111111111111111111111111111111111101001101001010010 '
1(
b11110100110100101001011011 #
b11110100110100101001011011 &
b11110100110100101001011011 2
#800000
b1000 $
b1000 -
b100001101000010001011010111010001111001011100000110010100100000011011100110010101100111 .
b1111111111111111111111111111111111111111111111101001101001010010 ,
b1111111111111111111111111111111111111111111111101001101001010010 +
#810000
b1000 )
b1000 *
