Lab08/Lab 8Q1/NextPClogic.v

module NextPClogic(NextPC, CurrentPC, SignExtImm64, Branch, ALUZero, Uncondbranch); 

    output reg [63:0] NextPC;   
    input [63:0] CurrentPC, SignExtImm64; // In and out
    input Branch, ALUZero, Uncondbranch; 
    

    always @(*) begin
        if(Uncondbranch || (Branch && ALUZero)) // Mux chooses 1
            NextPC = CurrentPC + SignExtImm64 * 4; // Shift offset

        else NextPC = CurrentPC + 4; // Mux chooses 0

    end


endmodule

Lab08/PCTest.v
`timescale 1ns / 1ps

////////////////////////////////////////////////////////////////////////////////
// Company: 
// Engineer:
//
// Create Date:   15:06:33 03/02/2009
// Design Name:   SignExtender
// Module Name:   E:/350/Lab7/SignExtenderTest.v
// Project Name:  SignExtender
// Target Device:  
// Tool versions:  
// Description: 
//
// Verilog Test Fixture created by ISE for module: SignExtender
//
// Dependencies:
// 
// Revision:
// Revision 0.01 - File Created
// Additional Comments:
// 
////////////////////////////////////////////////////////////////////////////////

`define STRLEN 25
module PCTest_v;
initial //This initial block used to dump all wire/reg values to dump file
    begin
     $dumpfile("PC.vcd"); // Fixed dump
     $dumpvars(0,PCTest_v);
    end
	task passTest;
		input [63:0] actualOut, expectedOut; // Output correct size, everything else copied
		input [`STRLEN*8:0] testType;
		inout [16:0] passed;
        // Checking if correct
		if(actualOut == expectedOut) begin $display ("%s passed", testType); passed = passed + 1; end
		else $display ("%s failed: %d should be %d", testType, actualOut, expectedOut);
	endtask
	
	task allPassed; // Checking if all passed
		input [16:0] passed;
		input [16:0] numTests;
		
		if(passed == numTests) $display ("All tests passed");
		else $display("Some tests failed");
	endtask
	
	task stim;
		input [63:0] newCurrentPC, newSignExtImm64; // Create new and set for inputs
		input newBranch, newALUZero, newUncondbranch;
		output [63:0] setCurrentPC, setSignExtImm64;
        output setBranch, setALUZero, setUncondbranch;
		
		begin
			#90;
			setCurrentPC = newCurrentPC; // Change old to new
			setSignExtImm64 = newSignExtImm64;
            setBranch = newBranch;
            setALUZero = newALUZero;
            setUncondbranch = newUncondbranch;
		end
	endtask
	
	// Inputs
	reg [63:0] CurrentPC, SignExtImm64;
	reg Branch, ALUZero, Uncondbranch;
	reg [16:0] passed;

	// Outputs
	wire [63:0] NextPC;

	// Instantiate the Unit Under Test (UUT)
	NextPClogic uut (
		.NextPC(NextPC), 
		.CurrentPC(CurrentPC), 
		.SignExtImm64(SignExtImm64),
        .Branch(Branch),
        .ALUZero(ALUZero),
        .Uncondbranch(Uncondbranch)
	);

	initial begin
		// Initialize Inputs
		CurrentPC = 0;
		SignExtImm64 = 0;
        Branch = 0;
        ALUZero = 0;
        Uncondbranch = 0;
		passed = 0;

        /*
        TESTS
        1 and 2. No branching, +4
        3 and 4. CBZ, one with Zero = 1 one with Zero = 0
        5 and 6. B one positive offset, one negative
        */

        /* FORMAT
        newCurrentPC, newSign, newBranch, newALUZero, newUncondbranch
        */

        // POSITIVE
        stim(64'hABCDF91891926572, 64'h0000723803738232, 0, 0, 0, CurrentPC, SignExtImm64, Branch, ALUZero, Uncondbranch);
        $display (CurrentPC," ", SignExtImm64, " ", Branch, " ", ALUZero, " ", Uncondbranch, " ", NextPC);
        #10; passTest(NextPC, 64'hABCDF91891926576, "No branch1, pos 000", passed);

        stim(64'h1287987ABCFF1120, 64'h7237778ADCDCD331, 0, 1, 0, CurrentPC, SignExtImm64, Branch, ALUZero, Uncondbranch);
        $display (CurrentPC," ", SignExtImm64, " ", Branch, " ", ALUZero, " ", Uncondbranch, " ", NextPC);
        #10; passTest(NextPC, 64'h1287987ABCFF1124, "No branch2, pos 010", passed);
        



        stim(64'h12982189723AB378, 64'h0000000127868718, 1, 0, 0, CurrentPC, SignExtImm64, Branch, ALUZero, Uncondbranch);
        $display (CurrentPC," ", SignExtImm64, " ", Branch, " ", ALUZero, " ", Uncondbranch, " ", NextPC);
        #10; passTest(NextPC, 64'h12982189723AB37C, "CBZ1, doesn't, pos 100", passed);

        stim(64'h8922837239181282, 64'h0000FFFFF109101B, 1, 1, 0, CurrentPC, SignExtImm64, Branch, ALUZero, Uncondbranch);
        $display (CurrentPC," ", SignExtImm64, " ", Branch, " ", ALUZero, " ", Uncondbranch, " ", NextPC);
        #10; passTest(NextPC, 64'h89268371FD3C52EE, "CBZ2, does, pos, 110", passed);
    


        stim(64'h00000012345BCDE2, 64'h000000000323387B, 0, 0, 1, CurrentPC, SignExtImm64, Branch, ALUZero, Uncondbranch);
        $display (CurrentPC," ", SignExtImm64, " ", Branch, " ", ALUZero, " ", Uncondbranch, " ", NextPC);
        #10; passTest(NextPC, 64'h1240E8AFCE, "B1, pos, 001", passed);

        stim(64'h0000010F3CDABFFF, 64'h0000000CDEF56124, 0, 1, 1, CurrentPC, SignExtImm64, Branch, ALUZero, Uncondbranch);
        $display (CurrentPC," ", SignExtImm64, " ", Branch, " ", ALUZero, " ", Uncondbranch, " ", NextPC);
        #10; passTest(NextPC, 64'h142B8B0448F, "B2, pos, 011", passed);

        stim(64'h0000111223A38787, 64'h000005646546CDEF, 1, 0, 1, CurrentPC, SignExtImm64, Branch, ALUZero, Uncondbranch);
        $display (CurrentPC," ", SignExtImm64, " ", Branch, " ", ALUZero, " ", Uncondbranch, " ", NextPC);
        #10; passTest(NextPC, 64'h26A3B8BEBF43, "B3, pos, 101", passed);

        stim(64'h0012328467BCD881, 64'h0000000872387CDE, 1, 1, 1, CurrentPC, SignExtImm64, Branch, ALUZero, Uncondbranch);
        $display (CurrentPC," ", SignExtImm64, " ", Branch, " ", ALUZero, " ", Uncondbranch, " ", NextPC);
        #10; passTest(NextPC, 64'h1232A6309ECBF9, "B4, pos, 111", passed);

        // NEGATIVE
        stim(64'h0001278387374444, 64'hFFFFEFACC8728818, 0, 0, 0, CurrentPC, SignExtImm64, Branch, ALUZero, Uncondbranch);
        $display (CurrentPC," ", SignExtImm64, " ", Branch, " ", ALUZero, " ", Uncondbranch, " ", NextPC);
        #10; passTest(NextPC, 64'h0001278387374448, "No branch1, pos 000", passed);

        stim(64'h2389748762387878, 64'hFFFFFFFFFE721767, 0, 1, 0, CurrentPC, SignExtImm64, Branch, ALUZero, Uncondbranch);
        $display (CurrentPC," ", SignExtImm64, " ", Branch, " ", ALUZero, " ", Uncondbranch, " ", NextPC);
        #10; passTest(NextPC, 64'h238974876238787C, "No branch2, pos 010", passed);
        



        stim(64'h2723872387238723, 64'hFFFFFF9812873182, 1, 0, 0, CurrentPC, SignExtImm64, Branch, ALUZero, Uncondbranch);
        $display (CurrentPC," ", SignExtImm64, " ", Branch, " ", ALUZero, " ", Uncondbranch, " ", NextPC);
        #10; passTest(NextPC, 64'h2723872387238727, "CBZ1, doesn't, pos 100", passed);

        stim(64'h0000233870187ABC, 64'hFFFFFFF812378181, 1, 1, 0, CurrentPC, SignExtImm64, Branch, ALUZero, Uncondbranch);
        $display (CurrentPC," ", SignExtImm64, " ", Branch, " ", ALUZero, " ", Uncondbranch, " ", NextPC);
        #10; passTest(NextPC, 64'h2318B8F680C0, "CBZ2, does, pos, 110", passed);
    


        stim(64'h000FFFF23787CDAB, 64'hFFFFFFFFFFFF1234, 0, 0, 1, CurrentPC, SignExtImm64, Branch, ALUZero, Uncondbranch);
        $display (CurrentPC," ", SignExtImm64, " ", Branch, " ", ALUZero, " ", Uncondbranch, " ", NextPC);
        #10; passTest(NextPC, 64'hFFFF23784167B, "B1, pos, 001", passed);

        stim(64'h0FFFFFFF321ABC64, 64'hFFFFFFF123879022, 0, 1, 1, CurrentPC, SignExtImm64, Branch, ALUZero, Uncondbranch);
        $display (CurrentPC," ", SignExtImm64, " ", Branch, " ", ALUZero, " ", Uncondbranch, " ", NextPC);
        #10; passTest(NextPC, 64'hFFFFFC3C038FCEC, "B2, neg, 011", passed);

        stim(64'h0000128023982998, 64'hFFFFFF38923983AB, 1, 0, 1, CurrentPC, SignExtImm64, Branch, ALUZero, Uncondbranch);
        $display (CurrentPC," ", SignExtImm64, " ", Branch, " ", ALUZero, " ", Uncondbranch, " ", NextPC);
        #10; passTest(NextPC, 64'hF626C7E3844, "B3, pos, 101", passed);

        stim(64'h00000011828827AA, 64'hFFFFFFFFFF298772, 1, 1, 1, CurrentPC, SignExtImm64, Branch, ALUZero, Uncondbranch);
        $display (CurrentPC," ", SignExtImm64, " ", Branch, " ", ALUZero, " ", Uncondbranch, " ", NextPC);
        #10; passTest(NextPC, 64'h117F2E4572, "B4, pos, 111", passed);
		
		allPassed(passed, 16); // Checking if everything worked
    end
      
endmodule

Lab08/PC.vcd
$date
	Mon Jun  9 14:45:00 2025
$end
$version
	Icarus Verilog
$end
$timescale
	1ps
$end
$scope module PCTest_v $end
$var wire 64 ! NextPC [63:0] $end
$var reg 1 " ALUZero $end
$var reg 1 # Branch $end
$var reg 64 $ CurrentPC [63:0] $end
$var reg 64 % SignExtImm64 [63:0] $end
$var reg 1 & Uncondbranch $end
$var reg 17 ' passed [16:0] $end
$scope module uut $end
$var wire 1 " ALUZero $end
$var wire 1 # Branch $end
$var wire 64 ( CurrentPC [63:0] $end
$var wire 64 ) SignExtImm64 [63:0] $end
$var wire 1 & Uncondbranch $end
$var reg 64 * NextPC [63:0] $end
$upscope $end
$scope task allPassed $end
$var reg 17 + numTests [16:0] $end
$var reg 17 , passed [16:0] $end
$upscope $end
$scope task passTest $end
$var reg 64 - actualOut [63:0] $end
$var reg 64 . expectedOut [63:0] $end
$var reg 17 / passed [16:0] $end
$var reg 201 0 testType [200:0] $end
$upscope $end
$scope task stim $end
$var reg 1 1 newALUZero $end
$var reg 1 2 newBranch $end
$var reg 64 3 newCurrentPC [63:0] $end
$var reg 64 4 newSignExtImm64 [63:0] $end
$var reg 1 5 newUncondbranch $end
$var reg 1 6 setALUZero $end
$var reg 1 7 setBranch $end
$var reg 64 8 setCurrentPC [63:0] $end
$var reg 64 9 setSignExtImm64 [63:0] $end
$var reg 1 : setUncondbranch $end
$upscope $end
$upscope $end
$enddefinitions $end
#0
$dumpvars
x:
bx 9
bx 8
x7
x6
05
b11100100011100000000011011100111000001000110010 4
b1010101111001101111110010001100010010001100100100110010101110010 3
02
01
bx 0
bx /
bx .
bx -
bx ,
bx +
b100 *
b0 )
b0 (
b0 '
0&
b0 %
b0 $
0#
0"
b100 !
$end
#90000
b1010101111001101111110010001100010010001100100100110010101110110 !
b1010101111001101111110010001100010010001100100100110010101110110 *
b11100100011100000000011011100111000001000110010 %
b11100100011100000000011011100111000001000110010 )
b1010101111001101111110010001100010010001100100100110010101110010 $
b1010101111001101111110010001100010010001100100100110010101110010 (
0:
06
07
b11100100011100000000011011100111000001000110010 9
b1010101111001101111110010001100010010001100100100110010101110010 8
#100000
11
b111001000110111011101111000101011011100110111001101001100110001 4
b1001010000111100110000111101010111100111111110001000100100000 3
b1 '
b1 /
b1001110011011110010000001100010011100100110000101101110011000110110100000110001001011000010000001110000011011110111001100100000001100000011000000110000 0
b1010101111001101111110010001100010010001100100100110010101110110 .
b1010101111001101111110010001100010010001100100100110010101110110 -
#190000
b1001010000111100110000111101010111100111111110001000100100100 !
b1001010000111100110000111101010111100111111110001000100100100 *
1"
b111001000110111011101111000101011011100110111001101001100110001 %
b111001000110111011101111000101011011100110111001101001100110001 )
b1001010000111100110000111101010111100111111110001000100100000 $
b1001010000111100110000111101010111100111111110001000100100000 (
16
b111001000110111011101111000101011011100110111001101001100110001 9
b1001010000111100110000111101010111100111111110001000100100000 8
#200000
01
12
b100100111100001101000011100011000 4
b1001010011000001000011000100101110010001110101011001101111000 3
b10 '
b10 /
b1001110011011110010000001100010011100100110000101101110011000110110100000110010001011000010000001110000011011110111001100100000001100000011000100110000 0
b1001010000111100110000111101010111100111111110001000100100100 .
b1001010000111100110000111101010111100111111110001000100100100 -
#290000
b1001010011000001000011000100101110010001110101011001101111100 !
b1001010011000001000011000100101110010001110101011001101111100 *
0"
1#
b100100111100001101000011100011000 %
b100100111100001101000011100011000 )
b1001010011000001000011000100101110010001110101011001101111000 $
b1001010011000001000011000100101110010001110101011001101111000 (
06
17
b100100111100001101000011100011000 9
b1001010011000001000011000100101110010001110101011001101111000 8
#300000
11
b111111111111111111110001000010010001000000011011 4
b1000100100100010100000110111001000111001000110000001001010000010 3
b11 '
b11 /
b1000011010000100101101000110001001011000010000001100100011011110110010101110011011011100010011101110100001011000010000001110000011011110111001100100000001100010011000000110000 0
b1001010011000001000011000100101110010001110101011001101111100 .
b1001010011000001000011000100101110010001110101011001101111100 -
#390000
b1000100100100110100000110111000111111101001111000101001011101110 !
b1000100100100110100000110111000111111101001111000101001011101110 *
1"
b111111111111111111110001000010010001000000011011 %
b111111111111111111110001000010010001000000011011 )
b1000100100100010100000110111001000111001000110000001001010000010 $
b1000100100100010100000110111001000111001000110000001001010000010 (
16
b111111111111111111110001000010010001000000011011 9
b1000100100100010100000110111001000111001000110000001001010000010 8
#400000
15
01
02
b11001000110011100001111011 4
b1001000110100010110111100110111100010 3
b100 '
b100 /
b100001101000010010110100011001000101100001000000110010001101111011001010111001100101100001000000111000001101111011100110010110000100000001100010011000100110000 0
b1000100100100110100000110111000111111101001111000101001011101110 .
b1000100100100110100000110111000111111101001111000101001011101110 -
#490000
b1001001000000111010001010111111001110 !
b1001001000000111010001010111111001110 *
1&
0"
0#
b11001000110011100001111011 %
b11001000110011100001111011 )
b1001000110100010110111100110111100010 $
b1001000110100010110111100110111100010 (
1:
06
07
b11001000110011100001111011 9
b1001000110100010110111100110111100010 8
#500000
11
b110011011110111101010110000100100100 4
b10000111100111100110110101011111111111111 3
b101 '
b101 /
b10000100011000100101100001000000111000001101111011100110010110000100000001100000011000000110001 0
b1001001000000111010001010111111001110 .
b1001001000000111010001010111111001110 -
#590000
b10100001010111000101100000100010010001111 !
b10100001010111000101100000100010010001111 *
1"
b110011011110111101010110000100100100 %
b110011011110111101010110000100100100 )
b10000111100111100110110101011111111111111 $
b10000111100111100110110101011111111111111 (
16
b110011011110111101010110000100100100 9
b10000111100111100110110101011111111111111 8
#600000
01
12
b1010110010001100101010001101100110111101111 4
b100010001001000100011101000111000011110000111 3
b110 '
b110 /
b10000100011001000101100001000000111000001101111011100110010110000100000001100000011000100110001 0
b10100001010111000101100000100010010001111 .
b10100001010111000101100000100010010001111 -
#690000
b1001101010001110111000101111101011111101000011 !
b1001101010001110111000101111101011111101000011 *
0"
1#
b1010110010001100101010001101100110111101111 %
b1010110010001100101010001101100110111101111 )
b100010001001000100011101000111000011110000111 $
b100010001001000100011101000111000011110000111 (
06
17
b1010110010001100101010001101100110111101111 9
b100010001001000100011101000111000011110000111 8
#700000
11
b100001110010001110000111110011011110 4
b10010001100101000010001100111101111001101100010000001 3
b111 '
b111 /
b10000100011001100101100001000000111000001101111011100110010110000100000001100010011000000110001 0
b1001101010001110111000101111101011111101000011 .
b1001101010001110111000101111101011111101000011 -
#790000
b10010001100101010011000110000100111101100101111111001 !
b10010001100101010011000110000100111101100101111111001 *
1"
b100001110010001110000111110011011110 %
b100001110010001110000111110011011110 )
b10010001100101000010001100111101111001101100010000001 $
b10010001100101000010001100111101111001101100010000001 (
16
b100001110010001110000111110011011110 9
b10010001100101000010001100111101111001101100010000001 8
#800000
05
01
02
b1111111111111111111011111010110011001000011100101000100000011000 4
b1001001111000001110000111001101110100010001000100 3
b1000 '
b1000 /
b10000100011010000101100001000000111000001101111011100110010110000100000001100010011000100110001 0
b10010001100101010011000110000100111101100101111111001 .
b10010001100101010011000110000100111101100101111111001 -
#890000
b1001001111000001110000111001101110100010001001000 !
b1001001111000001110000111001101110100010001001000 *
0&
0"
0#
b1111111111111111111011111010110011001000011100101000100000011000 %
b1111111111111111111011111010110011001000011100101000100000011000 )
b1001001111000001110000111001101110100010001000100 $
b1001001111000001110000111001101110100010001000100 (
0:
06
07
b1111111111111111111011111010110011001000011100101000100000011000 9
b1001001111000001110000111001101110100010001000100 8
#900000
11
b1111111111111111111111111111111111111110011100100001011101100111 4
b10001110001001011101001000011101100010001110000111100001111000 3
b1001 '
b1001 /
b1001110011011110010000001100010011100100110000101101110011000110110100000110001001011000010000001110000011011110111001100100000001100000011000000110000 0
b1001001111000001110000111001101110100010001001000 .
b1001001111000001110000111001101110100010001001000 -
#990000
b10001110001001011101001000011101100010001110000111100001111100 !
b10001110001001011101001000011101100010001110000111100001111100 *
1"
b1111111111111111111111111111111111111110011100100001011101100111 %
b1111111111111111111111111111111111111110011100100001011101100111 )
b10001110001001011101001000011101100010001110000111100001111000 $
b10001110001001011101001000011101100010001110000111100001111000 (
16
b1111111111111111111111111111111111111110011100100001011101100111 9
b10001110001001011101001000011101100010001110000111100001111000 8
#1000000
01
12
b1111111111111111111111111001100000010010100001110011000110000010 4
b10011100100011100001110010001110000111001000111000011100100011 3
b1010 '
b1010 /
b1001110011011110010000001100010011100100110000101101110011000110110100000110010001011000010000001110000011011110111001100100000001100000011000100110000 0
b10001110001001011101001000011101100010001110000111100001111100 .
b10001110001001011101001000011101100010001110000111100001111100 -
#1090000
b10011100100011100001110010001110000111001000111000011100100111 !
b10011100100011100001110010001110000111001000111000011100100111 *
0"
1#
b1111111111111111111111111001100000010010100001110011000110000010 %
b1111111111111111111111111001100000010010100001110011000110000010 )
b10011100100011100001110010001110000111001000111000011100100011 $
b10011100100011100001110010001110000111001000111000011100100011 (
06
17
b1111111111111111111111111001100000010010100001110011000110000010 9
b10011100100011100001110010001110000111001000111000011100100011 8
#1100000
11
b1111111111111111111111111111100000010010001101111000000110000001 4
b1000110011100001110000000110000111101010111100 3
b1011 '
b1011 /
b1000011010000100101101000110001001011000010000001100100011011110110010101110011011011100010011101110100001011000010000001110000011011110111001100100000001100010011000000110000 0
b10011100100011100001110010001110000111001000111000011100100111 .
b10011100100011100001110010001110000111001000111000011100100111 -
#1190000
b1000110001100010111000111101101000000011000000 !
b1000110001100010111000111101101000000011000000 *
1"
b1111111111111111111111111111100000010010001101111000000110000001 %
b1111111111111111111111111111100000010010001101111000000110000001 )
b1000110011100001110000000110000111101010111100 $
b1000110011100001110000000110000111101010111100 (
16
b1111111111111111111111111111100000010010001101111000000110000001 9
b1000110011100001110000000110000111101010111100 8
#1200000
15
01
02
b1111111111111111111111111111111111111111111111110001001000110100 4
b1111111111111111001000110111100001111100110110101011 3
b1100 '
b1100 /
b100001101000010010110100011001000101100001000000110010001101111011001010111001100101100001000000111000001101111011100110010110000100000001100010011000100110000 0
b1000110001100010111000111101101000000011000000 .
b1000110001100010111000111101101000000011000000 -
#1290000
b1111111111111111001000110111100001000001011001111011 !
b1111111111111111001000110111100001000001011001111011 *
1&
0"
0#
b1111111111111111111111111111111111111111111111110001001000110100 %
b1111111111111111111111111111111111111111111111110001001000110100 )
b1111111111111111001000110111100001111100110110101011 $
b1111111111111111001000110111100001111100110110101011 (
1:
06
07
b1111111111111111111111111111111111111111111111110001001000110100 9
b1111111111111111001000110111100001111100110110101011 8
#1300000
11
b1111111111111111111111111111000100100011100001111001000000100010 4
b111111111111111111111111111100110010000110101011110001100100 3
b1101 '
b1101 /
b10000100011000100101100001000000111000001101111011100110010110000100000001100000011000000110001 0
b1111111111111111001000110111100001000001011001111011 .
b1111111111111111001000110111100001000001011001111011 -
#1390000
b111111111111111111111100001111000000001110001111110011101100 !
b111111111111111111111100001111000000001110001111110011101100 *
1"
b1111111111111111111111111111000100100011100001111001000000100010 %
b1111111111111111111111111111000100100011100001111001000000100010 )
b111111111111111111111111111100110010000110101011110001100100 $
b111111111111111111111111111100110010000110101011110001100100 (
16
b1111111111111111111111111111000100100011100001111001000000100010 9
b111111111111111111111111111100110010000110101011110001100100 8
#1400000
01
12
b1111111111111111111111110011100010010010001110011000001110101011 4
b100101000000000100011100110000010100110011000 3
b1110 '
b1110 /
b10000100011001000101100001000000110111001100101011001110010110000100000001100000011000100110001 0
b111111111111111111111100001111000000001110001111110011101100 .
b111111111111111111111100001111000000001110001111110011101100 -
#1490000
b11110110001001101100011111100011100001000100 !
b11110110001001101100011111100011100001000100 *
0"
1#
b1111111111111111111111110011100010010010001110011000001110101011 %
b1111111111111111111111110011100010010010001110011000001110101011 )
b100101000000000100011100110000010100110011000 $
b100101000000000100011100110000010100110011000 (
06
17
b1111111111111111111111110011100010010010001110011000001110101011 9
b100101000000000100011100110000010100110011000 8
#1500000
11
b1111111111111111111111111111111111111111001010011000011101110010 4
b1000110000010100010000010011110101010 3
b1111 '
b1111 /
b10000100011001100101100001000000111000001101111011100110010110000100000001100010011000000110001 0
b11110110001001101100011111100011100001000100 .
b11110110001001101100011111100011100001000100 -
#1590000
b1000101111111001011100100010101110010 !
b1000101111111001011100100010101110010 *
1"
b1111111111111111111111111111111111111111001010011000011101110010 %
b1111111111111111111111111111111111111111001010011000011101110010 )
b1000110000010100010000010011110101010 $
b1000110000010100010000010011110101010 (
16
b1111111111111111111111111111111111111111001010011000011101110010 9
b1000110000010100010000010011110101010 8
#1600000
b10000 +
b10000 ,
b10000 '
b10000 /
b10000100011010000101100001000000111000001101111011100110010110000100000001100010011000100110001 0
b1000101111111001011100100010101110010 .
b1000101111111001011100100010101110010 -
