ALU\SignExtender/ALU.v
`define AND   4'b0000 // Defining operations
`define OR    4'b0001
`define ADD   4'b0010
`define SUB   4'b0110
`define PassB 4'b0111


module ALU(BusW, Zero, BusA, BusB, ALUCtrl);
    
    parameter n = 64;

    output reg [n-1:0] BusW; // Inputs and outputs
    input      [n-1:0] BusA, BusB;
    input      [3:0]   ALUCtrl;
    output reg Zero;
    
    always @(ALUCtrl or BusA or BusB) begin
        case(ALUCtrl)
            `AND: BusW = BusA & BusB;

            `OR:  BusW = BusA | BusB;

            `ADD: BusW = BusA + BusB;

            `SUB: BusW = BusA - BusB;

            `PassB: BusW = BusB;
            
        endcase

        if (BusW == 0) Zero = 1;
        else Zero = 0;
    end

endmodule

ALU\SignExtender/ALUTest.v
`timescale 1ns / 1ps

////////////////////////////////////////////////////////////////////////////////
// Company: 
// Engineer:
//
// Create Date:   10:02:47 03/05/2009
// Design Name:   ALU
// Module Name:   E:/350/Lab8/ALU/ALUTest.v
// Project Name:  ALU
// Target Device:  
// Tool versions:  
// Description: 
//
// Verilog Test Fixture created by ISE for module: ALU
//
// Dependencies:
// 
// Revision:
// Revision 0.01 - File Created
// Additional Comments:
// 
////////////////////////////////////////////////////////////////////////////////

`define STRLEN 32
module ALUTest_v;
initial
    begin
     $dumpfile("ALUTest.vcd"); // Fixed dump
     $dumpvars(0,ALUTest_v);
    end
	task passTest;
		input [64:0] actualOut, expectedOut;
		input [`STRLEN*8:0] testType;
		inout [14:0] passed;
	
		if(actualOut == expectedOut) begin $display ("%s passed", testType); passed = passed + 1; end
		else $display ("%s failed: %x should be %x", testType, actualOut, expectedOut);
	endtask
	
	task allPassed;
		input [14:0] passed;
		input [14:0] numTests;
		
		if(passed == numTests) $display ("All tests passed");
		else $display("Some tests failed");
	endtask

	// Inputs
	reg [63:0] BusA;
	reg [63:0] BusB;
	reg [3:0] ALUCtrl;
	reg [14:0] passed;

	// Outputs
	wire [63:0] BusW;
	wire Zero;

	// Instantiate the Unit Under Test (UUT)
	ALU uut (
		.BusW(BusW), 
		.Zero(Zero), 
		.BusA(BusA), 
		.BusB(BusB), 
		.ALUCtrl(ALUCtrl)
	);

	initial begin
		// Initialize Inputs
		BusA = 0;
		BusB = 0;
		ALUCtrl = 0;
		passed = 0;

         // Here is one example test vector, testing the ADD instruction:
        // AND
		{BusA, BusB, ALUCtrl} = {64'h21389, 64'h12398, 4'h0}; #40; passTest({Zero, BusW}, 65'h0388, "AND1", passed);
        {BusA, BusB, ALUCtrl} = {64'h0, 64'hFFFFFF, 4'h0}; #40; passTest({Zero, BusW}, {1'b1, 64'b0}, "AND2", passed);
        {BusA, BusB, ALUCtrl} = {64'h9776, 64'h54412, 4'h0}; #40; passTest({Zero, BusW}, 65'h0412, "AND3", passed);
        // OR 
        {BusA, BusB, ALUCtrl} = {64'h1921A, 64'hBC672, 4'h1}; #40; passTest({Zero, BusW}, 65'h0BD67A, "OR1", passed);
        {BusA, BusB, ALUCtrl} = {64'hF0F0F0, 64'H0F0F0F, 4'h1}; #40; passTest({Zero, BusW}, 65'h0FFFFFF, "OR2", passed);
        {BusA, BusB, ALUCtrl} = {64'hABCDEF, 64'h123456, 4'h1}; #40; passTest({Zero, BusW}, 65'h0BBFDFF, "OR3", passed);
        // ADD
        {BusA, BusB, ALUCtrl} = {64'h20, 64'h4500, 4'h2}; #40; passTest({Zero, BusW}, 65'h04520, "ADD1", passed);
        {BusA, BusB, ALUCtrl} = {64'h467, 64'h2329, 4'h2}; #40; passTest({Zero, BusW}, 65'h02790, "ADD2", passed);
        {BusA, BusB, ALUCtrl} = {64'h2387, 64'h9812, 4'h2}; #40; passTest({Zero, BusW}, 65'h0BB99, "ADD3", passed);
        // SUB
        {BusA, BusB, ALUCtrl} = {64'H9231, 64'h8128789, 4'h6}; #40; passTest({Zero, BusW}, {1'b0, 64'hFFFFFFFFF7EE0AA8}, "SUB1", passed);
        {BusA, BusB, ALUCtrl} = {64'hFFFA, 64'hFFFA, 4'h6}; #40; passTest({Zero, BusW}, {1'b1, 64'b0}, "SUB2", passed);
        {BusA, BusB, ALUCtrl} = {64'h29219A, 64'hBCD456, 4'h6}; #40; passTest({Zero, BusW}, {1'b0, 64'hFFFFFFFFFF6C4D44}, "SUB3", passed);
        // Pass B
        {BusA, BusB, ALUCtrl} = {64'h28179A, 64'h8799BC, 4'h7}; #40; passTest({Zero, BusW}, 65'h08799BC, "Pass1", passed);
        {BusA, BusB, ALUCtrl} = {64'h389DEA, 64'h7636A, 4'h7}; #40; passTest({Zero, BusW}, 65'h07636A, "Pass2", passed);
        {BusA, BusB, ALUCtrl} = {64'hFFFFFFF, 64'h127CEFF, 4'h7}; #40; passTest({Zero, BusW}, 65'h0127CEFF, "Pass3", passed);


		allPassed(passed, 15);
	end
      
endmodule

ALU\SignExtender/ALUTest.vcd
$date
	Thu Jun  5 11:26:18 2025
$end
$version
	Icarus Verilog
$end
$timescale
	1ps
$end
$scope module ALUTest_v $end
$var wire 1 ! Zero $end
$var wire 64 " BusW [63:0] $end
$var reg 4 # ALUCtrl [3:0] $end
$var reg 64 $ BusA [63:0] $end
$var reg 64 % BusB [63:0] $end
$var reg 15 & passed [14:0] $end
$scope module uut $end
$var wire 4 ' ALUCtrl [3:0] $end
$var wire 64 ( BusA [63:0] $end
$var wire 64 ) BusB [63:0] $end
$var reg 64 * BusW [63:0] $end
$var reg 1 ! Zero $end
$upscope $end
$scope task allPassed $end
$var reg 15 + numTests [14:0] $end
$var reg 15 , passed [14:0] $end
$upscope $end
$scope task passTest $end
$var reg 65 - actualOut [64:0] $end
$var reg 65 . expectedOut [64:0] $end
$var reg 15 / passed [14:0] $end
$var reg 257 0 testType [256:0] $end
$upscope $end
$upscope $end
$enddefinitions $end
#0
$dumpvars
bx 0
bx /
bx .
bx -
bx ,
bx +
b1110001000 *
b10010001110011000 )
b100001001110001001 (
b0 '
b0 &
b10010001110011000 %
b100001001110001001 $
b0 #
b1110001000 "
0!
$end
#40000
1!
b0 "
b0 *
b0 $
b0 (
b111111111111111111111111 %
b111111111111111111111111 )
b1 &
b1 /
b1000001010011100100010000110001 0
b1110001000 .
b1110001000 -
#80000
0!
b10000010010 "
b10000010010 *
b1001011101110110 $
b1001011101110110 (
b1010100010000010010 %
b1010100010000010010 )
b10 &
b10 /
b1000001010011100100010000110010 0
b10000000000000000000000000000000000000000000000000000000000000000 .
b10000000000000000000000000000000000000000000000000000000000000000 -
#120000
b10111101011001111010 "
b10111101011001111010 *
b11001001000011010 $
b11001001000011010 (
b10111100011001110010 %
b10111100011001110010 )
b1 #
b1 '
b11 &
b11 /
b1000001010011100100010000110011 0
b10000010010 .
b10000010010 -
#160000
b111111111111111111111111 "
b111111111111111111111111 *
b111100001111000011110000 $
b111100001111000011110000 (
b11110000111100001111 %
b11110000111100001111 )
b100 &
b100 /
b10011110101001000110001 0
b10111101011001111010 .
b10111101011001111010 -
#200000
b101110111111110111111111 "
b101110111111110111111111 *
b101010111100110111101111 $
b101010111100110111101111 (
b100100011010001010110 %
b100100011010001010110 )
b101 &
b101 /
b10011110101001000110010 0
b111111111111111111111111 .
b111111111111111111111111 -
#240000
b100010100100000 "
b100010100100000 *
b100000 $
b100000 (
b100010100000000 %
b100010100000000 )
b10 #
b10 '
b110 &
b110 /
b10011110101001000110011 0
b101110111111110111111111 .
b101110111111110111111111 -
#280000
b10011110010000 "
b10011110010000 *
b10001100111 $
b10001100111 (
b10001100101001 %
b10001100101001 )
b111 &
b111 /
b1000001010001000100010000110001 0
b100010100100000 .
b100010100100000 -
#320000
b1011101110011001 "
b1011101110011001 *
b10001110000111 $
b10001110000111 (
b1001100000010010 %
b1001100000010010 )
b1000 &
b1000 /
b1000001010001000100010000110010 0
b10011110010000 .
b10011110010000 -
#360000
b1111111111111111111111111111111111110111111011100000101010101000 "
b1111111111111111111111111111111111110111111011100000101010101000 *
b1001001000110001 $
b1001001000110001 (
b1000000100101000011110001001 %
b1000000100101000011110001001 )
b110 #
b110 '
b1001 &
b1001 /
b1000001010001000100010000110011 0
b1011101110011001 .
b1011101110011001 -
#400000
1!
b0 "
b0 *
b1111111111111010 $
b1111111111111010 (
b1111111111111010 %
b1111111111111010 )
b1010 &
b1010 /
b1010011010101010100001000110001 0
b1111111111111111111111111111111111110111111011100000101010101000 .
b1111111111111111111111111111111111110111111011100000101010101000 -
#440000
0!
b1111111111111111111111111111111111111111011011000100110101000100 "
b1111111111111111111111111111111111111111011011000100110101000100 *
b1010010010000110011010 $
b1010010010000110011010 (
b101111001101010001010110 %
b101111001101010001010110 )
b1011 &
b1011 /
b1010011010101010100001000110010 0
b10000000000000000000000000000000000000000000000000000000000000000 .
b10000000000000000000000000000000000000000000000000000000000000000 -
#480000
b100001111001100110111100 "
b100001111001100110111100 *
b1010000001011110011010 $
b1010000001011110011010 (
b100001111001100110111100 %
b100001111001100110111100 )
b111 #
b111 '
b1100 &
b1100 /
b1010011010101010100001000110011 0
b1111111111111111111111111111111111111111011011000100110101000100 .
b1111111111111111111111111111111111111111011011000100110101000100 -
#520000
b1110110001101101010 "
b1110110001101101010 *
b1110001001110111101010 $
b1110001001110111101010 (
b1110110001101101010 %
b1110110001101101010 )
b1101 &
b1101 /
b101000001100001011100110111001100110001 0
b100001111001100110111100 .
b100001111001100110111100 -
#560000
b1001001111100111011111111 "
b1001001111100111011111111 *
b1111111111111111111111111111 $
b1111111111111111111111111111 (
b1001001111100111011111111 %
b1001001111100111011111111 )
b1110 &
b1110 /
b101000001100001011100110111001100110010 0
b1110110001101101010 .
b1110110001101101010 -
#600000
b1111 +
b1111 ,
b1111 &
b1111 /
b101000001100001011100110111001100110011 0
b1001001111100111011111111 .
b1001001111100111011111111 -
